json2spark_mapper/__init__.py
json2spark_mapper/schema_mapper.py
json2spark_mapper/json_schema_drafts/__init__.py
json2spark_mapper/json_schema_drafts/drafts.py
json2spark_mapper/json_schema_readers/__init__.py
json2spark_mapper/json_schema_readers/schema_reader.py
json2spark_mapper/json_types/__init__.py
json2spark_mapper/json_types/array_resolver.py
json2spark_mapper/json_types/boolean_resolver.py
json2spark_mapper/json_types/integer_resolver.py
json2spark_mapper/json_types/number_resolver.py
json2spark_mapper/json_types/object_resolver.py
json2spark_mapper/json_types/resolver.py
json2spark_mapper/json_types/resolver_registry.py
json2spark_mapper/json_types/string_resolver.py
json2spark_mapper-0.1.0.dist-info/LICENSE
json2spark_mapper-0.1.0.dist-info/METADATA
json2spark_mapper-0.1.0.dist-info/WHEEL
json2spark_mapper-0.1.0.dist-info/top_level.txt
json2spark_mapper-0.1.0.dist-info/RECORD
