Metadata-Version: 2.1
Name: json2spark-mapper
Version: 0.1.0
Summary: Maps JSON schema types to Spark SQL types
Home-page: https://github.com/vdweij/json-data-type-to-spark-sql-type-mapper
Author: AvdW
Requires-Python: >=3.10
License-File: LICENSE
Requires-Dist: pyspark ==3.5.0
Provides-Extra: dev
Requires-Dist: pre-commit ~=3.5 ; extra == 'dev'
Requires-Dist: pytest ~=7.4 ; extra == 'dev'
Requires-Dist: pytest-cov ~=4.1 ; extra == 'dev'
